{
  "last_updated": "2026-07-17T00:45:34.304Z",
  "station_name": "Station meteo",
  "place": {
    "city": "Cagnac-les-Mines",
    "country": "FR",
    "timezone": "Europe/Paris",
    "location": [
      1.9667,
      43.9333
    ]
  },
  "indoor": {
    "temperature": 24.1,
    "humidity": 53,
    "co2": 1605,
    "noise": 38,
    "pressure": 1023.4,
    "abs_pressure": 985.6,
    "module_name": "Etage"
  },
  "outdoor": {
    "temperature": 27.3,
    "humidity": 68,
    "source": "netatmo"
  },
  "outdoor_source": "netatmo"
}