{
  "last_updated": "2026-07-06T16:30:59.968Z",
  "station_name": "Station meteo",
  "place": {
    "city": "Cagnac-les-Mines",
    "country": "FR",
    "timezone": "Europe/Paris",
    "location": [
      1.9667,
      43.9333
    ]
  },
  "indoor": {
    "temperature": 21,
    "humidity": 46,
    "co2": 567,
    "noise": 40,
    "pressure": 1023.8,
    "abs_pressure": 985.9,
    "module_name": "Etage"
  },
  "outdoor": {
    "temperature": 37.4,
    "humidity": 23,
    "source": "netatmo"
  },
  "outdoor_source": "netatmo"
}