{
  "last_updated": "2026-07-15T04:31:09.324Z",
  "station_name": "Station meteo",
  "place": {
    "city": "Cagnac-les-Mines",
    "country": "FR",
    "timezone": "Europe/Paris",
    "location": [
      1.9667,
      43.9333
    ]
  },
  "indoor": {
    "temperature": 23.7,
    "humidity": 53,
    "co2": 1517,
    "noise": 39,
    "pressure": 1021,
    "abs_pressure": 983.2,
    "module_name": "Etage"
  },
  "outdoor": {
    "temperature": 27.8,
    "humidity": 60,
    "source": "netatmo"
  },
  "outdoor_source": "netatmo"
}