{
  "last_updated": "2026-07-24T04:30:53.920Z",
  "station_name": "Station meteo",
  "place": {
    "city": "Cagnac-les-Mines",
    "country": "FR",
    "timezone": "Europe/Paris",
    "location": [
      1.9667,
      43.9333
    ]
  },
  "indoor": {
    "temperature": 23.8,
    "humidity": 47,
    "co2": 1652,
    "noise": 37,
    "pressure": 1020.3,
    "abs_pressure": 982.6,
    "module_name": "Etage"
  },
  "outdoor": {
    "temperature": 23.7,
    "humidity": 41,
    "source": "netatmo"
  },
  "outdoor_source": "netatmo"
}