{
  "last_updated": "2026-07-04T07:00:57.465Z",
  "station_name": "Station meteo",
  "place": {
    "city": "Cagnac-les-Mines",
    "country": "FR",
    "timezone": "Europe/Paris",
    "location": [
      1.9667,
      43.9333
    ]
  },
  "indoor": {
    "temperature": 23.2,
    "humidity": 51,
    "co2": 917,
    "noise": 37,
    "pressure": 1033.2,
    "abs_pressure": 995,
    "module_name": "Etage"
  },
  "outdoor": {
    "temperature": 21.9,
    "humidity": 60,
    "source": "netatmo"
  },
  "outdoor_source": "netatmo"
}