{
  "last_updated": "2026-07-12T13:01:09.950Z",
  "station_name": "Station meteo",
  "place": {
    "city": "Cagnac-les-Mines",
    "country": "FR",
    "timezone": "Europe/Paris",
    "location": [
      1.9667,
      43.9333
    ]
  },
  "indoor": {
    "temperature": 23.2,
    "humidity": 47,
    "co2": 1371,
    "noise": 41,
    "pressure": 1018.9,
    "abs_pressure": 981.2,
    "module_name": "Etage"
  },
  "outdoor": {
    "temperature": 35.7,
    "humidity": 34,
    "source": "netatmo"
  },
  "outdoor_source": "netatmo"
}