{
  "last_updated": "2026-07-13T00:31:06.912Z",
  "station_name": "Station meteo",
  "place": {
    "city": "Cagnac-les-Mines",
    "country": "FR",
    "timezone": "Europe/Paris",
    "location": [
      1.9667,
      43.9333
    ]
  },
  "indoor": {
    "temperature": 23.2,
    "humidity": 50,
    "co2": 1092,
    "noise": 38,
    "pressure": 1016.5,
    "abs_pressure": 978.9,
    "module_name": "Etage"
  },
  "outdoor": {
    "temperature": 28.6,
    "humidity": 40,
    "source": "netatmo"
  },
  "outdoor_source": "netatmo"
}