{
  "last_updated": "2026-07-25T00:01:04.749Z",
  "station_name": "Station meteo",
  "place": {
    "city": "Cagnac-les-Mines",
    "country": "FR",
    "timezone": "Europe/Paris",
    "location": [
      1.9667,
      43.9333
    ]
  },
  "indoor": {
    "temperature": 23.9,
    "humidity": 47,
    "co2": 1518,
    "noise": 38,
    "pressure": 1017.8,
    "abs_pressure": 980.2,
    "module_name": "Etage"
  },
  "outdoor": {
    "temperature": 27.5,
    "humidity": 40,
    "source": "netatmo"
  },
  "outdoor_source": "netatmo"
}